deepfree/__init__.py
deepfree/base/__init__.py
deepfree/base/_attribute.py
deepfree/base/_data.py
deepfree/base/_result.py
deepfree/base/_saver.py
deepfree/core/__init__.py
deepfree/core/_evaluate.py
deepfree/core/_layer.py
deepfree/core/_loss.py
deepfree/core/_model.py
deepfree/core/_submodel.py
deepfree/core/_train.py
deepfree/example/__init__.py
deepfree/example/classification_MINST.py
deepfree/example/graph.py
deepfree/example/test_func.py
deepfree/model/__init__.py
deepfree/model/ae.py
deepfree/model/ft_model.py
deepfree/model/pre_model.py
deepfree/model/rbm.py
deepfree-0.3.0.data/data/README.md
deepfree-0.3.0.dist-info/METADATA
deepfree-0.3.0.dist-info/RECORD
deepfree-0.3.0.dist-info/WHEEL
deepfree-0.3.0.dist-info/top_level.txt
