Metadata-Version: 2.1
Name: deepfree
Version: 0.3.0
Summary: keras-style deep network package for classification and prediction
Home-page: http://github.com/fuzimaoxinan/deepfree
Author: Zhuofu Pan
Author-email: 475366898@qq.com
Maintainer: Zhuofu Pan
Maintainer-email: 475366898@qq.com
License: UNKNOWN
Keywords: deep network,deep learning,DBN,SAE
Platform: any
Classifier: Programming Language :: Python :: 3
Classifier: License :: OSI Approved :: MIT License
Classifier: Operating System :: OS Independent
